dlslime/__init__.py
dlslime/_slime_c.cpython-311-x86_64-linux-gnu.so
dlslime/buffer/__init__.py
dlslime/buffer/inter/__init__.py
dlslime/buffer/inter/all_gather_inter_ll_buffer.py
dlslime/buffer/inter/init_nvshmem.py
dlslime/buffer/intra/__init__.py
dlslime/buffer/intra/all_to_all_intra_ll_buffer.py
dlslime/lib_slime_device.so
dlslime/lib_slime_engine.so
dlslime/lib_slime_rdma.so
dlslime/libnuma.so
dlslime/libnuma.so.1
dlslime/libnuma.so.1.0.0
dlslime/share/cmake/dlslime/dlslimeConfig.cmake
dlslime/share/cmake/dlslime/dlslimeConfigVersion.cmake
dlslime/share/cmake/dlslime/dlslimeTargets-release.cmake
dlslime/share/cmake/dlslime/dlslimeTargets.cmake
dlslime/utils/json_merge_manually.py
dlslime/utils/json_merger.py
include/dlslime/dlslime/device/cuda/cuda_signal.h
include/dlslime/dlslime/device/cuda/nvtx_helper.h
include/dlslime/dlslime/device/device_api.h
include/dlslime/dlslime/device/host/host_signal.h
include/dlslime/dlslime/device/signal.h
include/dlslime/dlslime/engine/ascend_direct/ascend_direct_transport.h
include/dlslime/dlslime/engine/assignment.h
include/dlslime/dlslime/engine/dlpack.h
include/dlslime/dlslime/engine/nvlink/memory_pool.h
include/dlslime/dlslime/engine/nvlink/nvlink_endpoint.h
include/dlslime/dlslime/engine/nvlink/nvlink_future.h
include/dlslime/dlslime/engine/nvshmem/buffer.h
include/dlslime/dlslime/engine/nvshmem/nvshmem_context.h
include/dlslime/dlslime/engine/offloading/offloading.h
include/dlslime/dlslime/engine/rdma/ibv_helper.h
include/dlslime/dlslime/engine/rdma/memory_pool.h
include/dlslime/dlslime/engine/rdma/rdma_assignment.h
include/dlslime/dlslime/engine/rdma/rdma_channel.h
include/dlslime/dlslime/engine/rdma/rdma_common.h
include/dlslime/dlslime/engine/rdma/rdma_config.h
include/dlslime/dlslime/engine/rdma/rdma_context.h
include/dlslime/dlslime/engine/rdma/rdma_context_pool.h
include/dlslime/dlslime/engine/rdma/rdma_endpoint.h
include/dlslime/dlslime/engine/rdma/rdma_env.h
include/dlslime/dlslime/engine/rdma/rdma_future.h
dlslime-0.0.2.post1.dist-info/METADATA
dlslime-0.0.2.post1.dist-info/WHEEL
dlslime-0.0.2.post1.dist-info/licenses/LICENSE
dlslime-0.0.2.post1.dist-info/RECORD
