Metadata-Version: 2.2
Name: dlslime
Version: 0.0.2.post1
Summary: DLSlime Transfer Engine
Author-Email: JimyMa <hit16s105116@gmail.com>
Classifier: Development Status :: 3 - Alpha
Classifier: Intended Audience :: Developers
Classifier: Intended Audience :: Science/Research
Classifier: Intended Audience :: System Administrators
Classifier: License :: OSI Approved :: BSD License
Classifier: Operating System :: POSIX :: Linux
Classifier: Operating System :: Unix
Classifier: Programming Language :: C++
Classifier: Programming Language :: Python :: 3
Classifier: Topic :: System :: Networking
Classifier: Topic :: System :: Systems Administration
Project-URL: Homepage, https://github.com/DeepLink-org/DLSlime.git
Project-URL: Repository, https://github.com/DeepLink-org/DLSlime.git
Requires-Python: >=3.8
Requires-Dist: xxhash
Requires-Dist: pydantic>=2.0
Requires-Dist: scikit-build-core>=0.10
Requires-Dist: pybind11>=2.12
